ak_file/__init__.py
ak_file/main.py
ak_file/sanitizer.py
ak_file/search.py
ak_file-0.1.4.dist-info/LICENSE
ak_file-0.1.4.dist-info/WHEEL
ak_file-0.1.4.dist-info/METADATA
ak_file-0.1.4.dist-info/RECORD
