Metadata-Version: 2.1
Name: ak_file
Version: 0.1.4
Summary: File Parsing function
Author-email: Arun Kishore <pypi@rpakishore.co.in>
Requires-Python: >=3.11.0
Classifier: License :: OSI Approved :: MIT License
Requires-Dist: cryptography>=41.0.3
Requires-Dist: ipykernel ; extra == "dev"
Requires-Dist: icecream ; extra == "dev"
Requires-Dist: pytest ; extra == "test"
Project-URL: Home, https://github.com/rpakishore/ak-file
Provides-Extra: dev
Provides-Extra: test
